vfmc/__init__.py
vfmc/__main__.py
vfmc/app.py
vfmc/attempt.py
vfmc/insertions.py
vfmc/orientation.py
vfmc/palette.py
vfmc/prefs.py
vfmc/viz.py
vfmc-1.5.1.dist-info/licenses/LICENSE
vfmc-1.5.1.dist-info/METADATA
vfmc-1.5.1.dist-info/WHEEL
vfmc-1.5.1.dist-info/entry_points.txt
vfmc-1.5.1.dist-info/top_level.txt
vfmc-1.5.1.dist-info/RECORD
