Metadata-Version: 2.4
Name: vfmc
Version: 1.5.1
Summary: A virtual FMC attempt tool
Author-email: Rodney Kinney <rodney.m.kinney@gmail.com>
License:                                  Apache License
Project-URL: Homepage, https://github.com/rodneykinney/VFMC
Classifier: Programming Language :: Python :: 3
Requires-Python: >=3.9
License-File: LICENSE
Requires-Dist: pyquaternion~=0.9
Requires-Dist: PyQt5~=5.15.0
Requires-Dist: vfmc_core==1.5.1
Provides-Extra: dev
Requires-Dist: black~=25.1; extra == "dev"
Requires-Dist: flake8~=7.2; extra == "dev"
Requires-Dist: maturin~=1.8; extra == "dev"
Requires-Dist: pyinstaller~=6.12; extra == "dev"
Requires-Dist: build~=1.2; extra == "dev"
Requires-Dist: twine~=6.1; extra == "dev"
Dynamic: license-file
